Metadata-Version: 1.0
Name: slugifygui
Version: 2019.1.29.1633
Summary: graphical user interface to slugify text
Home-page: https://github.com/wdbm/slugifygui
Author: Will Breaden Madden
Author-email: wbm@protonmail.ch
License: GPLv3
Platform: UNKNOWN
